[
  {"era_slug": "criacao", "title": "A Criação", "description": "Deus cria os céus e a terra em seis dias.", "event_type": "event", "year_approx": -4000, "year_display": "~4000 a.C.", "order_index": 1},
  {"era_slug": "criacao", "title": "Adão e Eva no Éden", "description": "Os primeiros humanos vivem em harmonia perfeita com Deus.", "event_type": "event", "year_approx": -3990, "year_display": "~3990 a.C.", "order_index": 2},
  {"era_slug": "criacao", "title": "A Queda", "description": "Adão e Eva desobedecem a Deus e são expulsos do Éden.", "event_type": "event", "year_approx": -3985, "year_display": "~3985 a.C.", "order_index": 3},
  {"era_slug": "criacao", "title": "Caim mata Abel", "description": "O primeiro assassinato da história humana.", "event_type": "event", "year_approx": -3850, "year_display": "~3850 a.C.", "order_index": 4},
  {"era_slug": "criacao", "title": "Noé e o Dilúvio", "description": "Deus purifica a terra e faz aliança com Noé pelo arco-íris.", "event_type": "covenant", "year_approx": -2350, "year_display": "~2350 a.C.", "order_index": 5},
  {"era_slug": "criacao", "title": "Torre de Babel", "description": "A humanidade tenta construir uma torre até o céu. Deus confunde as línguas e dispersa os povos.", "event_type": "event", "year_approx": -2200, "year_display": "~2200 a.C.", "order_index": 6},
  {"era_slug": "patriarcas", "title": "Chamado de Abrão", "description": "Deus chama Abrão de Ur para uma terra desconhecida.", "event_type": "covenant", "year_approx": -2091, "year_display": "~2091 a.C.", "order_index": 1},
  {"era_slug": "patriarcas", "title": "Nascimento de Isaac", "description": "Sara, aos 90 anos, dá à luz o filho da promessa.", "event_type": "birth", "year_approx": -2066, "year_display": "~2066 a.C.", "order_index": 2},
  {"era_slug": "patriarcas", "title": "Sacrifício de Isaac", "description": "Deus testa Abraão pedindo o sacrifício de Isaac — e provê um cordeiro substituto.", "event_type": "event", "year_approx": -2050, "year_display": "~2050 a.C.", "order_index": 3},
  {"era_slug": "patriarcas", "title": "Jacó foge de Esaú", "description": "Após roubar a bênção de seu irmão, Jacó foge para Harã.", "event_type": "event", "year_approx": -1929, "year_display": "~1929 a.C.", "order_index": 4},
  {"era_slug": "patriarcas", "title": "José é vendido como escravo", "description": "Os irmãos de José o vendem para mercadores egípcios por 20 peças de prata.", "event_type": "event", "year_approx": -1898, "year_display": "~1898 a.C.", "order_index": 5},
  {"era_slug": "patriarcas", "title": "José se torna governador do Egito", "description": "O Faraó coloca José como segundo no comando para administrar o Egito.", "event_type": "event", "year_approx": -1886, "year_display": "~1886 a.C.", "order_index": 6},
  {"era_slug": "egito-exodus", "title": "Moisés nasce", "description": "Um bebê hebreu é salvo das águas do Nilo e adotado pela filha do Faraó.", "event_type": "birth", "year_approx": -1526, "year_display": "~1526 a.C.", "order_index": 1},
  {"era_slug": "egito-exodus", "title": "A Sarça Ardente", "description": "Deus chama Moisés no deserto de Midiã para liderar a libertação de Israel.", "event_type": "event", "year_approx": -1446, "year_display": "~1446 a.C.", "order_index": 2},
  {"era_slug": "egito-exodus", "title": "As Dez Pragas", "description": "Dez pragas devastam o Egito até o Faraó libertar os israelitas.", "event_type": "miracle", "year_approx": -1446, "year_display": "~1446 a.C.", "order_index": 3},
  {"era_slug": "egito-exodus", "title": "O Êxodo", "description": "Cerca de 2 milhões de israelitas saem do Egito após 430 anos de escravidão.", "event_type": "event", "year_approx": -1446, "year_display": "~1446 a.C.", "order_index": 4},
  {"era_slug": "egito-exodus", "title": "A Travessia do Mar Vermelho", "description": "O exército egípcio os persegue. Deus abre o mar, Israel passa em terra seca.", "event_type": "miracle", "year_approx": -1446, "year_display": "~1446 a.C.", "order_index": 5},
  {"era_slug": "egito-exodus", "title": "Os Dez Mandamentos", "description": "Deus entrega a Lei a Moisés no Monte Sinai.", "event_type": "covenant", "year_approx": -1446, "year_display": "~1446 a.C.", "order_index": 6},
  {"era_slug": "reino", "title": "Davi é ungido rei", "description": "Samuel unge Davi, o mais jovem filho de Jessé, como rei de Israel.", "event_type": "event", "year_approx": -1025, "year_display": "~1025 a.C.", "order_index": 1},
  {"era_slug": "reino", "title": "Davi derrota Golias", "description": "O jovem pastor mata o gigante filisteu com uma pedra e uma funda.", "event_type": "event", "year_approx": -1020, "year_display": "~1020 a.C.", "order_index": 2},
  {"era_slug": "reino", "title": "Davi torna-se rei em Jerusalém", "description": "Davi conquista Jerusalém e a estabelece como capital do reino.", "event_type": "event", "year_approx": -1003, "year_display": "~1003 a.C.", "order_index": 3},
  {"era_slug": "reino", "title": "Salomão constrói o Templo", "description": "O grandioso Templo de Salomão é construído em Jerusalém.", "event_type": "event", "year_approx": -966, "year_display": "~966 a.C.", "order_index": 4},
  {"era_slug": "exilio", "title": "Babilônia destrói Jerusalém", "description": "Nabucodonosor destrói o Templo e leva o povo cativo para a Babilônia.", "event_type": "war", "year_approx": -586, "year_display": "586 a.C.", "order_index": 1},
  {"era_slug": "retorno", "title": "Decreto de Ciro", "description": "O rei persa Ciro permite que os exilados judeus retornem à sua terra.", "event_type": "event", "year_approx": -538, "year_display": "538 a.C.", "order_index": 1},
  {"era_slug": "retorno", "title": "Reconstrução do Templo", "description": "O Segundo Templo é reconstruído em Jerusalém.", "event_type": "event", "year_approx": -516, "year_display": "516 a.C.", "order_index": 2},
  {"era_slug": "jesus-nt", "title": "Nascimento de Jesus", "description": "Jesus nasce em Belém, numa manjedoura, anunciado por anjos e adorado por pastores.", "event_type": "birth", "year_approx": -4, "year_display": "~4 a.C.", "order_index": 1},
  {"era_slug": "jesus-nt", "title": "Batismo de Jesus", "description": "João Batista batiza Jesus no Rio Jordão. O Espírito desce como pomba e uma voz do céu fala.", "event_type": "event", "year_approx": 27, "year_display": "~27 d.C.", "order_index": 2},
  {"era_slug": "jesus-nt", "title": "Início do ministério de Jesus", "description": "Jesus começa a pregar: 'Arrependei-vos, porque o Reino dos Céus está próximo.'", "event_type": "event", "year_approx": 27, "year_display": "~27 d.C.", "order_index": 3},
  {"era_slug": "jesus-nt", "title": "Crucificação de Jesus", "description": "Jesus é crucificado em Jerusalém sob Pôncio Pilatos.", "event_type": "event", "year_approx": 30, "year_display": "~30 d.C.", "order_index": 9},
  {"era_slug": "jesus-nt", "title": "Ressurreição de Jesus", "description": "No terceiro dia, Jesus ressuscita dos mortos — o evento central da história cristã.", "event_type": "miracle", "year_approx": 30, "year_display": "~30 d.C.", "order_index": 10},
  {"era_slug": "igreja-primitiva", "title": "Pentecostes", "description": "O Espírito Santo é derramado sobre os discípulos. Três mil pessoas se convertem. A Igreja nasce.", "event_type": "event", "year_approx": 30, "year_display": "~30 d.C.", "order_index": 1},
  {"era_slug": "igreja-primitiva", "title": "Conversão de Paulo", "description": "Saulo, perseguidor da Igreja, encontra Jesus ressurreto no caminho de Damasco e é transformado.", "event_type": "event", "year_approx": 35, "year_display": "~35 d.C.", "order_index": 2},
  {"era_slug": "igreja-primitiva", "title": "João escreve o Apocalipse", "description": "O apóstolo João recebe e escreve a Revelação na ilha de Patmos.", "event_type": "prophecy", "year_approx": 95, "year_display": "~95 d.C.", "order_index": 10}
]
